uni2ts/__about__.py
uni2ts/__init__.py
uni2ts/callbacks/HuggingFaceCheckpoint.py
uni2ts/callbacks/__init__.py
uni2ts/common/__init__.py
uni2ts/common/core.py
uni2ts/common/env.py
uni2ts/common/hydra_util.py
uni2ts/common/sampler.py
uni2ts/common/torch_util.py
uni2ts/common/typing.py
uni2ts/data/__init__.py
uni2ts/data/dataset.py
uni2ts/data/loader.py
uni2ts/data/builder/__init__.py
uni2ts/data/builder/_base.py
uni2ts/data/builder/simple.py
uni2ts/data/builder/lotsa_v1/README.md
uni2ts/data/builder/lotsa_v1/__init__.py
uni2ts/data/builder/lotsa_v1/__main__.py
uni2ts/data/builder/lotsa_v1/_base.py
uni2ts/data/builder/lotsa_v1/buildings_bench.py
uni2ts/data/builder/lotsa_v1/cloudops_tsf.py
uni2ts/data/builder/lotsa_v1/cmip6.py
uni2ts/data/builder/lotsa_v1/era5.py
uni2ts/data/builder/lotsa_v1/gluonts.py
uni2ts/data/builder/lotsa_v1/largest.py
uni2ts/data/builder/lotsa_v1/lib_city.py
uni2ts/data/builder/lotsa_v1/others.py
uni2ts/data/builder/lotsa_v1/proenfo.py
uni2ts/data/builder/lotsa_v1/subseasonal.py
uni2ts/data/indexer/__init__.py
uni2ts/data/indexer/_base.py
uni2ts/data/indexer/hf_dataset_indexer.py
uni2ts/distribution/__init__.py
uni2ts/distribution/_base.py
uni2ts/distribution/laplace.py
uni2ts/distribution/log_normal.py
uni2ts/distribution/mixture.py
uni2ts/distribution/negative_binomial.py
uni2ts/distribution/normal.py
uni2ts/distribution/pareto.py
uni2ts/distribution/student_t.py
uni2ts/eval_util/__init__.py
uni2ts/eval_util/_hf_dataset.py
uni2ts/eval_util/_lsf_dataset.py
uni2ts/eval_util/_pf_dataset.py
uni2ts/eval_util/data.py
uni2ts/eval_util/evaluation.py
uni2ts/eval_util/metrics.py
uni2ts/eval_util/plot.py
uni2ts/loss/__init__.py
uni2ts/loss/packed/__init__.py
uni2ts/loss/packed/_base.py
uni2ts/loss/packed/distribution.py
uni2ts/loss/packed/normalized.py
uni2ts/loss/packed/percentage_error.py
uni2ts/loss/packed/point.py
uni2ts/loss/packed/quantile.py
uni2ts/model/__init__.py
uni2ts/model/moirai/__init__.py
uni2ts/model/moirai/finetune.py
uni2ts-2.0.0.dist-info/METADATA
uni2ts-2.0.0.dist-info/WHEEL
uni2ts-2.0.0.dist-info/licenses/LICENSE.txt
uni2ts-2.0.0.dist-info/RECORD
