Metadata-Version: 2.4
Name: uni2ts
Version: 2.0.0
Summary: Unified Training of Universal Time Series Forecasting Transformers
Author: Akshat Kumar, Caiming Xiong, Silvio Savarese, Doyen Sahoo
Author-email: Gerald Woo <gwoo@salesforce.com>, Chenghao Liu <chenghao.liu@salesforce.com>, Juncheng Liu <juncheng.liu@salesforce.com>, Taha Aksu <iaksu@salesforce.com>, Xu Liu <xu.liu@salesforce.com>
Maintainer-email: Gerald Woo <gwoo@salesforce.com>, Juncheng Liu <juncheng.liu@salesforce.com>
License: Apache License Version 2.0
License-File: LICENSE.txt
Keywords: Deep Learning,PyTorch,Time Series Forecasting,Transformer
Classifier: Development Status :: 3 - Alpha
Classifier: Programming Language :: Python
Classifier: Topic :: Scientific/Engineering :: Artificial Intelligence
Requires-Python: >=3.10
Requires-Dist: datasets~=2.17.1
Requires-Dist: einops==0.7.*
Requires-Dist: gluonts~=0.14.3
Requires-Dist: huggingface-hub>=0.23.0
Requires-Dist: hydra-core==1.3
Requires-Dist: jax[cpu]
Requires-Dist: jaxtyping~=0.2.24
Requires-Dist: lightning>=2.0
Requires-Dist: multiprocess
Requires-Dist: numpy~=1.26.0
Requires-Dist: orjson
Requires-Dist: python-dotenv==1.0.0
Requires-Dist: safetensors
Requires-Dist: scipy~=1.11.3
Requires-Dist: tensorboard
Requires-Dist: torch<2.5,>=2.1
Provides-Extra: build-lotsa
Requires-Dist: buildings-bench; extra == 'build-lotsa'
Requires-Dist: pyreadr; extra == 'build-lotsa'
Requires-Dist: subseasonal-data; extra == 'build-lotsa'
Requires-Dist: tables; extra == 'build-lotsa'
Provides-Extra: dev
Requires-Dist: black[jupyter]==24.2.0; extra == 'dev'
Requires-Dist: hatch; extra == 'dev'
Requires-Dist: isort; extra == 'dev'
Requires-Dist: pre-commit; extra == 'dev'
Requires-Dist: pytest-timeout==2.2.0; extra == 'dev'
Requires-Dist: pytest==7.4.3; extra == 'dev'
Provides-Extra: notebook
Requires-Dist: ipywidgets; extra == 'notebook'
Requires-Dist: jupyter; extra == 'notebook'
Requires-Dist: matplotlib; extra == 'notebook'
